picodoc/__init__.py
picodoc/config.py
picodoc/functions.py
picodoc/models.py
picodoc/picodoc.py
tests/__init__.py
tests/config.py
tests/test_convert.py
tests/test_dict.py
tests/test_list.py
tests/test_setting.py
picodoc-0.1.7.dist-info/LICENSE
picodoc-0.1.7.dist-info/METADATA
picodoc-0.1.7.dist-info/WHEEL
picodoc-0.1.7.dist-info/top_level.txt
picodoc-0.1.7.dist-info/RECORD
