Metadata-Version: 2.1
Name: picodoc
Version: 0.1.7
Summary: A small document database
Home-page: https://github.com/donkere-vader/picodoc
Author: Donkere Vader
Author-email: donkere.v@gmail.com
License: UNKNOWN
Project-URL: Bug Tracker, https://github.com/donkere-vader/picodoc/issues
Platform: UNKNOWN
Classifier: Programming Language :: Python :: 3
Classifier: License :: OSI Approved :: MIT License
Classifier: Operating System :: OS Independent
Requires-Python: >=3.6
License-File: LICENSE
Requires-Dist: peewee (>=3.14.4)
